{"title": "Information Leakage", "priority": "P0", "baseline_impact": false, "description": {"ns2:div": {"ns2:p": {"@class": "align_left", "#text": "The organization protects the information system from information leakage due to electromagnetic signals emanations."}}}, "supplemental_guidance": {"ns2:div": {"ns2:p": {"@class": "align_left", "#text": "The security categorization of the information system (with respect to confidentiality) and organizational security policy guides the application of safeguards and countermeasures employed to protect the information system against information leakage due to electromagnetic signals emanations."}}}, "references": {"@href": "http://csrc.nist.gov/publications/fips/fips199/FIPS-PUB-199-final.pdf", "#text": "FIPS Publication 199"}, "control_enhancements": {"@sequence": "1", "description": {"ns2:div": {"ns2:p": {"@class": "align_left", "#text": "The organization ensures that information system components, associated data communications, and networks are protected in accordance with:"}, "ns2:ol": {"ns2:li": "national emissions and TEMPEST policies and procedures; and (ii) the sensitivity of the information being transmitted."}}}}}