{"title": "Information Input Validation", "priority": "P1", "baseline_impact": false, "description": {"ns2:div": {"ns2:p": {"@class": "align_left", "#text": "The information system checks the validity of information inputs."}}}, "supplemental_guidance": {"ns2:div": {"ns2:p": {"@class": "align_left", "#text": "Rules for checking the valid syntax and semantics of information system inputs (e.g., character set, length, numerical range, acceptable values) are in place to verify that inputs match specified definitions for format and content. Inputs passed to interpreters are prescreened to prevent the content from being unintentionally interpreted as commands."}}}, "references": false, "control_enhancements": false}